WindowsPythonWheel/setup.py
omniorb_py-4.3.1.data/data/DLLs/COS4.lib
omniorb_py-4.3.1.data/data/DLLs/COS431_rt.lib
omniorb_py-4.3.1.data/data/DLLs/COS431_rtd.lib
omniorb_py-4.3.1.data/data/DLLs/COS431_vc15_rt.dll
omniorb_py-4.3.1.data/data/DLLs/COS431_vc15_rtd.dll
omniorb_py-4.3.1.data/data/DLLs/COS4_rt.lib
omniorb_py-4.3.1.data/data/DLLs/COS4_rtd.lib
omniorb_py-4.3.1.data/data/DLLs/COS4d.lib
omniorb_py-4.3.1.data/data/DLLs/COSDynamic4.lib
omniorb_py-4.3.1.data/data/DLLs/COSDynamic431_rt.lib
omniorb_py-4.3.1.data/data/DLLs/COSDynamic431_rtd.lib
omniorb_py-4.3.1.data/data/DLLs/COSDynamic431_vc15_rt.dll
omniorb_py-4.3.1.data/data/DLLs/COSDynamic431_vc15_rtd.dll
omniorb_py-4.3.1.data/data/DLLs/COSDynamic4_rt.lib
omniorb_py-4.3.1.data/data/DLLs/COSDynamic4_rtd.lib
omniorb_py-4.3.1.data/data/DLLs/COSDynamic4d.lib
omniorb_py-4.3.1.data/data/DLLs/_omniConnMgmt.pyd
omniorb_py-4.3.1.data/data/DLLs/_omnicodesets.pyd
omniorb_py-4.3.1.data/data/DLLs/_omnihttpCrypto.pyd
omniorb_py-4.3.1.data/data/DLLs/_omnihttpTP.pyd
omniorb_py-4.3.1.data/data/DLLs/_omnipy.pyd
omniorb_py-4.3.1.data/data/DLLs/_omnisslTP.pyd
omniorb_py-4.3.1.data/data/DLLs/msvcstub.lib
omniorb_py-4.3.1.data/data/DLLs/msvcstubd.lib
omniorb_py-4.3.1.data/data/DLLs/omniCodeSets4.lib
omniorb_py-4.3.1.data/data/DLLs/omniCodeSets4.pdb
omniorb_py-4.3.1.data/data/DLLs/omniCodeSets431_rt.lib
omniorb_py-4.3.1.data/data/DLLs/omniCodeSets431_rtd.lib
omniorb_py-4.3.1.data/data/DLLs/omniCodeSets431_vc15_rt.dll
omniorb_py-4.3.1.data/data/DLLs/omniCodeSets431_vc15_rtd.dll
omniorb_py-4.3.1.data/data/DLLs/omniCodeSets4_rt.lib
omniorb_py-4.3.1.data/data/DLLs/omniCodeSets4_rtd.lib
omniorb_py-4.3.1.data/data/DLLs/omniCodeSets4d.lib
omniorb_py-4.3.1.data/data/DLLs/omniCodeSets4d.pdb
omniorb_py-4.3.1.data/data/DLLs/omniConnectionMgmt4.lib
omniorb_py-4.3.1.data/data/DLLs/omniConnectionMgmt4.pdb
omniorb_py-4.3.1.data/data/DLLs/omniConnectionMgmt431_rt.lib
omniorb_py-4.3.1.data/data/DLLs/omniConnectionMgmt431_rtd.lib
omniorb_py-4.3.1.dist-info/METADATA
omniorb_py-4.3.1.dist-info/WHEEL
omniorb_py-4.3.1.dist-info/top_level.txt
omniorb_py-4.3.1.dist-info/RECORD
