Metadata-Version: 2.1
Name: omniorb-py
Version: 4.3.1
Summary: Ready to use omniorb distribution for windows
Home-page: http://omniorb.sourceforge.net/
Author: Duncan Grisby
Author-email: duncan@grisby.org
License: LGPL for libraries, GPL for tools
Classifier: Programming Language :: Python :: 3
Classifier: License :: OSI Approved :: GNU Library or Lesser General Public License (LGPL)
Classifier: Operating System :: Microsoft :: Windows
Requires-Python: >=3.10
